[{"Name":"Ravi Bishnoi","Runs":"0","Balls":"0","Fours":"0","Sixes":"0","SR":"0.00","Date":" Oct 24 2020","opponent":"Kings XI Punjab","venue":" Dubai","Result":"Kings XI Punjabwon."},{"Name":"Ravi Bishnoi","Runs":"1","Balls":"5","Fours":"0","Sixes":"0","SR":"20.00","Date":" Oct 1 2020","opponent":"Mumbai Indians","venue":" Abu Dhabi","Result":"Mumbai Indianswon."},{"Name":"Ravi Bishnoi","Runs":"6","Balls":"7","Fours":"1","Sixes":"0","SR":"85.71","Date":" Oct 8 2020","opponent":"Sunrisers Hyderabad","venue":" Dubai","Result":"Sunrisers Hyderabadwon."}]