[{"Name":"Abhishek Sharma","Runs":"10","Balls":"13","Fours":"0","Sixes":"0","SR":"76.92","Date":" Oct 4 2020","opponent":"Mumbai Indians","venue":" Sharjah","Result":"Mumbai Indianswon."},{"Name":"Abhishek Sharma","Runs":"8","Balls":"5","Fours":"0","Sixes":"1","SR":"160.00","Date":" Oct 31 2020","opponent":"Royal Challengers Bangalore","venue":" Sharjah","Result":"Sunrisers Hyderabadwon."},{"Name":"Abhishek Sharma","Runs":"31","Balls":"24","Fours":"4","Sixes":"1","SR":"129.17","Date":" Oct 2 2020","opponent":"Chennai Super Kings","venue":" Dubai","Result":"Sunrisers Hyderabadwon."},{"Name":"Abhishek Sharma","Runs":"12","Balls":"6","Fours":"1","Sixes":"1","SR":"200.00","Date":" Oct 8 2020","opponent":"Kings XI Punjab","venue":" Dubai","Result":"Sunrisers Hyderabadwon."},{"Name":"Abhishek Sharma","Runs":"2","Balls":"3","Fours":"0","Sixes":"0","SR":"66.67","Date":" Sep 26 2020","opponent":"Kolkata Knight Riders","venue":" Abu Dhabi","Result":"Kolkata Knight Riderswon."},{"Name":"Abhishek Sharma","Runs":"1","Balls":"1","Fours":"0","Sixes":"0","SR":"100.00","Date":" Sep 29 2020","opponent":"Delhi Capitals","venue":" Abu Dhabi","Result":"Sunrisers Hyderabadwon."},{"Name":"Abhishek Sharma","Runs":"7","Balls":"4","Fours":"1","Sixes":"0","SR":"175.00","Date":" Sep 21 2020","opponent":"Royal Challengers Bangalore","venue":" Dubai","Result":"Royal Challengers Bangalorewon."}]